{
  "id": "3",
  "title": "From Dissections to Discoveries: Why Research is Your Next Best Move",
  "authors": ["Dr. Jane Smith", "Dr. John Doe"],
  "abstract": "When I first picked up a scalpel in anatomy class, I thought,...",
  "content": "When I first picked up a scalpel in anatomy class, I thought, 'This is it. I've reached the peak of medical school.' Turns out, I was wrong. You see, slicing through cadavers might make you feel like a modern-day Indiana Jones, but real discovery happens far from the dissection table. It happens in research.\n\nYes, I know what you're thinking. Research can sound intimidating—words like 'hypothesis' and 'methodology' tend to have that effect. But here's the thing: research is just like solving a complex medical mystery. And if you're already a medical student (or aspiring to be one), you're halfway there. We've all had those sleepless nights memorizing anatomical terms that you'll swear have no use in real life. But in research? Everything connects. Suddenly, that obscure muscle you once questioned has a role to play in the bigger picture of human health.\n\nWhen I first dove into research, I had no idea what I was doing—zero clue. But every 'failed' experiment taught me more than my successes ever did. And here's where the humor comes in: research is just like life in medical school. Sometimes you'll spend hours working, only to realize you've been on the wrong track the whole time. But guess what? That's part of the fun. It's where learning happens.\n\nSo, to those of you new to research, don't be afraid to make mistakes. The greatest discoveries often come from unexpected places. You're not just studying medicine—you're building knowledge that could change the future. Go on, take the plunge. Trust me, research is where the real adventure begins.",
  "publishedDate": "2024-10-23"
}
